xython/__init__.py
xython/xy_auto.py
xython/xy_chart.py
xython/xy_color.py
xython/xy_common.py
xython/xy_common_hwp.py
xython/xy_common_map.py
xython/xy_db.py
xython/xy_example.py
xython/xy_excel.py
xython/xy_excel_event.py
xython/xy_grid.py
xython/xy_grid_model.py
xython/xy_grid_original.py
xython/xy_grid_widget.py
xython/xy_hwp.py
xython/xy_hwp_common.py
xython/xy_list.py
xython/xy_map.py
xython/xy_map_common.py
xython/xy_outlook.py
xython/xy_re.py
xython/xy_time.py
xython/xy_util.py
xython/xy_util2.py
xython/xy_web.py
xython/xy_word.py
xython-4.2.0.dist-info/METADATA
xython-4.2.0.dist-info/WHEEL
xython-4.2.0.dist-info/top_level.txt
xython-4.2.0.dist-info/RECORD
