Metadata-Version: 2.4
Name: xython
Version: 4.2.0
Summary: win32com + python + Office Automation = xython, (for easy automation for excel, word, outlook, regex, color, hwp, etc BY python & win32com)
Home-page: https://www.xython.co.kr
Author: sj park
Author-email: sjpkorea@naver.com
Project-URL: Documentation, https://sjpkorea.github.io/xython.github.io/
Project-URL: Link 1, https://www.xython.co.kr
Classifier: License :: OSI Approved :: GNU General Public License v3 (GPLv3)
Requires-Python: >=3.8
Dynamic: author
Dynamic: author-email
Dynamic: classifier
Dynamic: description
Dynamic: description-content-type
Dynamic: home-page
Dynamic: project-url
Dynamic: requires-python
Dynamic: summary
